pyowc/__init__.py
pyowc/calibration.py
pyowc/configuration.py
pyowc/core/__init__.py
pyowc/core/finders.py
pyowc/core/stats.py
pyowc/data/__init__.py
pyowc/data/fetchers.py
pyowc/data/wrangling.py
pyowc/helper.py
pyowc/plot/__init__.py
pyowc/plot/dashboard.py
pyowc/plot/plots.py
pyowc/plot/utils.py
pyowc/tests/__init__.py
pyowc/tests/calibration_test.py
pyowc/tests/configuration_test.py
pyowc/tests/core_finders_test.py
pyowc/tests/core_stats_test.py
pyowc/tests/data_fetchers_test.py
pyowc/tests/data_wrangling_test.py
pyowc/tests/plot_dashboard_test.py
pyowc/tests/plot_plots_test.py
pyowc/tests/test_config.json
pyowc/tests/utilities_test.py
pyowc/utilities.py
argodmqc_owc-0.1.11.dist-info/LICENSE
argodmqc_owc-0.1.11.dist-info/METADATA
argodmqc_owc-0.1.11.dist-info/WHEEL
argodmqc_owc-0.1.11.dist-info/entry_points.txt
argodmqc_owc-0.1.11.dist-info/RECORD
