Metadata-Version: 2.3
Name: argodmqc_owc
Version: 0.1.11
Summary: OWC salinity calibration in Python
License: Apache-2.0
Requires-Python: >=3.12,<4.0
Classifier: License :: OSI Approved :: Apache Software License
Classifier: Programming Language :: Python :: 3
Classifier: Programming Language :: Python :: 3.12
Classifier: Programming Language :: Python :: 3.13
Requires-Dist: gsw (==3.6.20)
Requires-Dist: matplotlib (==3.10.5)
Requires-Dist: numpy (==2.3.2)
Requires-Dist: pandas (==2.3.1)
Requires-Dist: poetry-dynamic-versioning (>=1.1.0,<2.0.0)
Requires-Dist: pydantic (>=2.11.7,<3.0.0)
Requires-Dist: pymatreader (==1.1.0)
Requires-Dist: pyshp (==2.3.1)
Requires-Dist: scipy (==1.16.1)
Project-URL: Bug Tracker, https://github.com/euroargodev/argodmqc_owc/issues
Project-URL: Homepage, https://github.com/euroargodev/argodmqc_owc
